LICENSE.md
README.md
setup.cfg
setup.py
PyConsoleMenu/__init__.py
PyConsoleMenu/base.py
PyConsoleMenu/menu.py
PyConsoleMenu/misc.py
PyConsoleMenu.egg-info/PKG-INFO
PyConsoleMenu.egg-info/SOURCES.txt
PyConsoleMenu.egg-info/dependency_links.txt
PyConsoleMenu.egg-info/requires.txt
PyConsoleMenu.egg-info/top_level.txt