Metadata-Version: 2.1
Name: PyConsoleMenu
Version: 1.0.4
Summary: A simple console menu system using curses
Home-page: https://github.com/BaggerFast/PyConsoleMenu
Author: BaggerFast (Aleksandrov Daniil)
Author-email: riosha3@gmail.com
License: MIT
Keywords: python menu,console menu,menu,curses menu,python console menu
Platform: UNKNOWN
Classifier: Intended Audience :: Developers
Classifier: License :: OSI Approved :: MIT License
Classifier: Operating System :: OS Independent
Classifier: Programming Language :: Python :: 3
Classifier: Programming Language :: Python :: 3 :: Only
Classifier: Programming Language :: Python :: 3.7
Classifier: Programming Language :: Python :: 3.8
Classifier: Programming Language :: Python :: 3.9
Classifier: Programming Language :: Python :: 3.10
Classifier: Programming Language :: Python :: Implementation :: CPython
Classifier: Programming Language :: Python :: Implementation :: PyPy
Classifier: Programming Language :: Python
Classifier: Topic :: Software Development :: Libraries :: Python Modules
Requires-Python: >=3.7
License-File: LICENSE.md
